README.rst
setup.cfg
setup.py
tox_bitbucket_status.py
tox_bitbucket_status.egg-info/PKG-INFO
tox_bitbucket_status.egg-info/SOURCES.txt
tox_bitbucket_status.egg-info/dependency_links.txt
tox_bitbucket_status.egg-info/entry_points.txt
tox_bitbucket_status.egg-info/requires.txt
tox_bitbucket_status.egg-info/top_level.txt