Metadata-Version: 1.0
Name: tox-bitbucket-status
Version: 1.0
Summary: Update bitbucket status for each env
Home-page: https://bitbucket.org/schinckel/tox-bitbucket-status/
Author: Matthew Schinckel
Author-email: matt@schinckel.net
License: UNKNOWN
Platform: UNKNOWN
